pyvisco/__init__.py
pyvisco/_version.py
pyvisco/inter.py
pyvisco/load.py
pyvisco/master.py
pyvisco/opt.py
pyvisco/out.py
pyvisco/prony.py
pyvisco/shift.py
pyvisco/styles.py
pyvisco/verify.py
pyvisco-1.0.4.dist-info/licenses/LICENSE
pyvisco-1.0.4.dist-info/METADATA
pyvisco-1.0.4.dist-info/WHEEL
pyvisco-1.0.4.dist-info/top_level.txt
pyvisco-1.0.4.dist-info/RECORD
